jtree/__init__.py
jtree/__main__.py
jtree/utils.py
jtree/widgets.py
jtree/css/layout.css
jtree-0.2.7.dist-info/LICENSE
jtree-0.2.7.dist-info/METADATA
jtree-0.2.7.dist-info/WHEEL
jtree-0.2.7.dist-info/entry_points.txt
jtree-0.2.7.dist-info/top_level.txt
jtree-0.2.7.dist-info/RECORD
