Metadata-Version: 2.1
Name: jtree
Version: 0.2.7
Summary: jtree is a command line interface (CLI) for displaying JavaScript Object Notation (JSON) in a tree view
Author-email: Oleksis Fraga Menéndez <oleksis.fraga@gmail.com>
License: MIT License
Project-URL: Homepage, https://github.com/oleksis/jtree
Project-URL: Tracker, https://github.com/oleksis/jtree/issues
Keywords: json,terminal,tui,tool,explorer,viewer
Classifier: License :: OSI Approved :: MIT License
Classifier: Development Status :: 4 - Beta
Classifier: Environment :: Console
Classifier: Programming Language :: Python
Classifier: Programming Language :: Python :: 3
Requires-Python: >=3.7
License-File: LICENSE
Requires-Dist: textual >=0.11.0
Provides-Extra: ci
Requires-Dist: tox ; extra == 'ci'
Provides-Extra: dev
Requires-Dist: bumpver ; extra == 'dev'
Requires-Dist: pip-tools ; extra == 'dev'
Requires-Dist: pipdeptree ; extra == 'dev'
Requires-Dist: debugpy ; extra == 'dev'
Requires-Dist: check-manifest ; extra == 'dev'
Requires-Dist: check-wheel-contents ; extra == 'dev'
Requires-Dist: tox ; extra == 'dev'
Requires-Dist: tomli >=1.1.0 ; (python_version < "3.11") and extra == 'dev'
Provides-Extra: format
Requires-Dist: black ; extra == 'format'
Requires-Dist: isort ; extra == 'format'
Provides-Extra: test
Requires-Dist: pytest ; extra == 'test'
